goark/__init__.py
goark/main.py
goark/tests.py
goark/tools.py
goark/utilities.py
goark-0.1.dist-info/METADATA
goark-0.1.dist-info/WHEEL
goark-0.1.dist-info/top_level.txt
goark-0.1.dist-info/RECORD
